fwts/__init__.py
fwts/cli.py
fwts/completions.py
fwts/config.py
fwts/docker.py
fwts/focus.py
fwts/git.py
fwts/github.py
fwts/hooks.py
fwts/lifecycle.py
fwts/linear.py
fwts/setup.py
fwts/tmux.py
fwts/tui.py
fwts-0.1.28.dist-info/METADATA
fwts-0.1.28.dist-info/WHEEL
fwts-0.1.28.dist-info/entry_points.txt
fwts-0.1.28.dist-info/licenses/LICENSE
fwts-0.1.28.dist-info/RECORD
