Metadata-Version: 2.4
Name: fwts
Version: 0.1.28
Summary: Git worktree workflow manager for feature development
Project-URL: Homepage, https://github.com/laudiacay/featurebox
Project-URL: Repository, https://github.com/laudiacay/featurebox
Project-URL: Issues, https://github.com/laudiacay/featurebox/issues
Author-email: Claudia Richoux <claudia@laudiacay.com>
License-Expression: MIT
License-File: LICENSE
Keywords: cli,git,linear,tmux,workflow,worktree
Classifier: Development Status :: 4 - Beta
Classifier: Environment :: Console
Classifier: Intended Audience :: Developers
Classifier: License :: OSI Approved :: MIT License
Classifier: Operating System :: MacOS
Classifier: Operating System :: POSIX :: Linux
Classifier: Programming Language :: Python :: 3
Classifier: Programming Language :: Python :: 3.10
Classifier: Programming Language :: Python :: 3.11
Classifier: Programming Language :: Python :: 3.12
Classifier: Topic :: Software Development :: Version Control :: Git
Requires-Python: >=3.10
Requires-Dist: anyio>=4.0.0
Requires-Dist: httpx>=0.25.0
Requires-Dist: readchar>=4.0.0
Requires-Dist: rich>=13.0.0
Requires-Dist: tomli>=2.0.0; python_version < '3.11'
Requires-Dist: typer>=0.9.0
Provides-Extra: dev
Requires-Dist: pyright>=1.1.0; extra == 'dev'
Requires-Dist: pytest-asyncio>=0.21.0; extra == 'dev'
Requires-Dist: pytest-cov>=4.0.0; extra == 'dev'
Requires-Dist: pytest>=7.0.0; extra == 'dev'
Requires-Dist: ruff>=0.1.0; extra == 'dev'
